webint_media/__init__.py
webint_media/templates/__init__.py
webint_media/templates/index.html
webint_media/templates/media_added.html
webint_media/templates/media_deleted.html
webint_media-0.0.54.dist-info/METADATA
webint_media-0.0.54.dist-info/entry_points.txt
webint_media-0.0.54.dist-info/WHEEL
webint_media-0.0.54.dist-info/RECORD
