Metadata-Version: 2.1
Name: webint-media
Version: 0.0.54
Summary: manage media on your website
License: AGPL-3.0-or-later
Author: Angelo Gladding
Author-email: angelo@ragt.ag
Requires-Python: >=3.10,<3.11
Classifier: License :: OSI Approved :: GNU Affero General Public License v3 or later (AGPLv3+)
Classifier: Programming Language :: Python :: 3
Classifier: Programming Language :: Python :: 3.10
Requires-Dist: webint (>=0.0)
Requires-Dist: yt-dlp (>=2023.3.4,<2024.0.0)
